my_simple_jwt_auth/__init__.py
my_simple_jwt_auth/my_simple_jwt_auth.py
my_simple_jwt_authentication-1.0.4.dist-info/LICENSE.txt
my_simple_jwt_authentication-1.0.4.dist-info/METADATA
my_simple_jwt_authentication-1.0.4.dist-info/WHEEL
my_simple_jwt_authentication-1.0.4.dist-info/top_level.txt
my_simple_jwt_authentication-1.0.4.dist-info/RECORD
